llm_vm/client.py
llm_vm/config.py
llm_vm/data_path.py
llm_vm/guided_completion.py
llm_vm/onsite_llm.py
llm_vm/settings.default.toml
llm_vm/vector_db.py
llm_vm/agents/agent_interface.py
llm_vm/agents/FLAT/agent.py
llm_vm/agents/FLAT/typings.py
llm_vm/agents/FLAT/agent_helper/bothandler.py
llm_vm/agents/FLAT/agent_helper/business_logic.py
llm_vm/agents/FLAT/agent_helper/replacer.py
llm_vm/agents/FLAT/agent_helper/tool_utils.py
llm_vm/agents/FLAT/agent_helper/tools.py
llm_vm/agents/FLAT/agent_helper/use_tool.py
llm_vm/agents/FLAT/agent_helper/utils.py
llm_vm/agents/FLAT/agent_helper/requests/call_llm.py
llm_vm/agents/FLAT/agent_helper/requests/call_open_ai.py
llm_vm/agents/FLAT/models/get_decision_model.py
llm_vm/agents/FLAT/models/helpers/check_model_status.py
llm_vm/agents/FLAT/models/helpers/delete_model.py
llm_vm/agents/FLAT/models/helpers/persist_models.py
llm_vm/agents/FLAT/models/helpers/upload_model.py
llm_vm/agents/FLAT/models/utils/answer_from_memory_model/answer_from_memory_model_data.py
llm_vm/agents/FLAT/models/utils/answer_from_memory_model/get_asm_as_jsonl.py
llm_vm/agents/FLAT/models/utils/question_split_model/get_qs_as_jsonl.py
llm_vm/agents/FLAT/models/utils/question_split_model/question_split_model_data.py
llm_vm/agents/FLAT/models/utils/tool_input_model/get_tool_input_as_jsonl.py
llm_vm/agents/FLAT/models/utils/tool_input_model/tool_input_model_data.py
llm_vm/agents/FLAT/models/utils/tool_picker_model/get_tp_as_jsonl.py
llm_vm/agents/FLAT/models/utils/tool_picker_model/get_training_tools.py
llm_vm/agents/FLAT/models/utils/tool_picker_model/tool_picker_model_data.py
llm_vm/agents/REBEL/agent.py
llm_vm/agents/REBEL/bothandler.py
llm_vm/agents/REBEL/test_agent.py
llm_vm/agents/REBEL/utils.py
llm_vm/completion/data_synthesis.py
llm_vm/completion/optimize.py
llm_vm/server/main.py
llm_vm/server/routes.py
llm_vm/utils/keys.py
llm_vm/utils/labels.py
llm_vm/utils/print_types.py
llm_vm/utils/ram.py
llm_vm/utils/tools.py
llm_vm/utils/typings_llm.py
llm_vm-0.1.55.dist-info/LICENSE
llm_vm-0.1.55.dist-info/METADATA
llm_vm-0.1.55.dist-info/WHEEL
llm_vm-0.1.55.dist-info/entry_points.txt
llm_vm-0.1.55.dist-info/top_level.txt
llm_vm-0.1.55.dist-info/RECORD
