Metadata-Version: 2.1
Name: llm-vm
Version: 0.1.55
Summary: An Open-Source AGI Server for Open-Source LLMs
Author-email: Anarchy Team <matt@anarchy.ai>
License: MIT
Requires-Python: >=3.10
License-File: LICENSE
Requires-Dist: dynaconf >=3.2.0
Requires-Dist: openai >=0.27.6
Requires-Dist: numpy >=1.22.4
Requires-Dist: watchdog >=3.0.0
Requires-Dist: xdg >=6.0.0
Requires-Dist: accelerate >=0.21.0
Requires-Dist: transformers >=4.31.0
Requires-Dist: ctransformers >=0.2.24
Requires-Dist: flask >=2.3.2
Requires-Dist: flask-cors >=4.0.0
Requires-Dist: llama-index >=0.7.7
Requires-Dist: python-Levenshtein >=0.21.1
Requires-Dist: bs4 >=0.0.1
Requires-Dist: sentencepiece >=0.1.99
Requires-Dist: sentence-transformers >=2.2.2
Requires-Dist: requests >=2.26.0
Requires-Dist: spacy >=3.5.3
Requires-Dist: outlines >=0.0.1
Requires-Dist: gradio >=3.42.0
Requires-Dist: backoff >=2.2.1
Requires-Dist: peft >=0.5.0
Requires-Dist: trl >=0.7.2
Requires-Dist: pinecone-client >=2.2.4
Requires-Dist: PyPDF2 >=3.0.1
Requires-Dist: weaviate-client >=3.25.3
Requires-Dist: python-dotenv >=1.0.0
Provides-Extra: dev
Requires-Dist: black >=23.7.0 ; extra == 'dev'
Requires-Dist: mypy >=1.5.1 ; extra == 'dev'
